{"sections":{"main":{"type":"main-product","blocks":{"vendor":{"type":"vendor","disabled":true,"settings":{}},"title":{"type":"title","settings":{"heading_tag":"h2"}},"badges":{"type":"badges","settings":{}},"price":{"type":"price","settings":{"show_taxes_notice":false}},"rating":{"type":"rating","settings":{"show_empty":false}},"payment_terms":{"type":"payment_terms","settings":{}},"offer_GbjtNt":{"type":"offer","settings":{"text_alignment":"start","icon_position":"aligned","icon":"none","icon_width":24,"title":"","content":"<p><strong>This pack does not contain the tech module. <\/strong><a href=\"#bottom\" title=\"#bottom\">Buy it now<\/a><\/p>","background":"#d4eff8","text_color":"#1a1a1a"}},"separator":{"type":"separator","settings":{}},"description":{"type":"description","settings":{"collapse_content":false}},"variant_picker":{"type":"variant_picker","settings":{"hide_sold_out_variants":false,"stack_blocks":true,"selector_mode":"block","color_mode":"variant","size_chart_page":""}},"quantity_selector":{"type":"quantity_selector","settings":{}},"buy_buttons":{"type":"buy_buttons","settings":{"show_payment_button":true,"show_gift_card_recipient":true,"atc_button_background":"","atc_button_text_color":"","payment_button_background":"","payment_button_text_color":""}},"text_a9hkVY":{"type":"text","settings":{"text":"<p><strong>Free delivery. 30 day money back guarantee. 1 year warranty<\/strong><\/p>"}},"d6741f35-9e65-493c-a4a0-140f0b783b55":{"type":"collapsible_text","disabled":true,"settings":{"title":"Description","content":"<p>Share some content to your customers about your products.<\/p>"}},"66adc232-a3f4-4c5f-b113-31a723e19152":{"type":"collapsible_text","disabled":true,"settings":{"title":"Product Specs","content":"<p>Share some content to your customers about your products.<\/p>"}},"1d6e7401-ba3d-4085-b3b0-184d3608fc6d":{"type":"collapsible_text","settings":{"title":"Shipping","content":"<p><strong>Fast Delivery to:<\/strong><\/p><ul><li>UK 2-3 days <\/li><li>USA 4-5 days<\/li><li>EU 5-10 days<\/li><li>Canada 8-10 days <\/li><li>Australia 8-10 days<\/li><\/ul>"}}},"block_order":["vendor","title","badges","price","rating","payment_terms","offer_GbjtNt","separator","description","variant_picker","quantity_selector","buy_buttons","text_a9hkVY","d6741f35-9e65-493c-a4a0-140f0b783b55","66adc232-a3f4-4c5f-b113-31a723e19152","1d6e7401-ba3d-4085-b3b0-184d3608fc6d"],"settings":{"full_width":true,"show_fixed_add_to_cart":true,"desktop_media_width":55,"desktop_media_layout":"carousel_thumbnails_bottom","mobile_media_size":"expanded","mobile_carousel_control":"free_scroll","enable_video_autoplay":false,"enable_video_looping":true,"enable_image_zoom":true,"max_image_zoom_level":3,"background":"","background_gradient":"","text_color":"","input_background":"rgba(0,0,0,0)","input_text_color":""}},"d9d08b5d-a836-459e-8579-0fd215508612":{"type":"images-row-animated","blocks":{"190ef3a5-21bf-4d5f-8eca-fd950ae78d38":{"type":"tab","settings":{"ring-size":""}},"1f2d0461-3312-465a-881e-b0141ed628a2":{"type":"tab","settings":{"ring-size":""}},"1993a88c-34d5-41ce-89bc-90d2568920fb":{"type":"tab","settings":{"ring-size":"XL"}},"da81ac74-7138-4776-af6b-e914b057c570":{"type":"tab","settings":{"ring-size":"L"}},"c3ca0d35-ff4a-440c-888d-529e8c77d26e":{"type":"tab","settings":{"ring-size":"M"}},"90e671db-06b7-4159-8a89-d818bea93ef2":{"type":"tab","settings":{"ring-size":"S"}},"bd6f7e99-b6b2-46c2-9005-4641f0fa402a":{"type":"tab","settings":{"ring-size":"XS"}}},"block_order":["190ef3a5-21bf-4d5f-8eca-fd950ae78d38","1f2d0461-3312-465a-881e-b0141ed628a2","1993a88c-34d5-41ce-89bc-90d2568920fb","da81ac74-7138-4776-af6b-e914b057c570","c3ca0d35-ff4a-440c-888d-529e8c77d26e","90e671db-06b7-4159-8a89-d818bea93ef2","bd6f7e99-b6b2-46c2-9005-4641f0fa402a"],"settings":{"background_color":"#ffffff","background_gradient":"","sizes-bottom":6,"header-color":"#0ec3ff","body_text":"Different size for different uses","add-text-1":"Handlebar mount","add-text-2":"Strap mount","font-size":"var(--text-h3)","font-weight":"900","font-style":"normal","text-align":"center","main-image":"shopify:\/\/shop_images\/Desktop.png","main-image-mobile":"shopify:\/\/shop_images\/Mob_235b9a11-bd53-478d-8167-f796f281dfe7.png","add-image":"shopify:\/\/shop_images\/335157210ef722146ecc9aff44f9fbd7.png"}},"8179674e-8606-4b6b-85f8-5b3d943ebb4c":{"type":"featured-collection","settings":{"collection":"colour-packs","products":[],"full_width":true,"stack_products":false,"anable-drop-shadow":true,"shadow-hover":false,"shadow-hover-color":"#ffffff","show_progress_bar":false,"products_count":6,"products_per_row_mobile":"1","products_per_row_desktop":4,"subheading":"","title":"Life in Colors","header-color":"#1a1a1a","content":"","link_url":"","link_text":"View all","background":"","background_gradient":"","text_color":"","heading_color":"","heading_gradient":"","product_card_background":"","product_card_text_color":""}},"5c3c5d27-589a-469d-bbbe-474a58ca1927":{"type":"multi-column","blocks":{"template--16346234257596__5c3c5d27-589a-469d-bbbe-474a58ca1927-item-1":{"type":"item","settings":{"image":"shopify:\/\/shop_images\/Frame_288_f616394d-9d58-4ee2-95c9-9cec8ab9affc.svg","column_size":"3","title":"Choose","heading_tag":"h4","content":"<p>How to use your ArcX. Either insert the tech into a ring or use it in a strap mount and attach to handlebars, kayak paddles, ski poles or anything else.<\/p>","blob-color":"#0ec3ff","link_url":"","link_text":"","link_style":"link"}},"template--16346234257596__5c3c5d27-589a-469d-bbbe-474a58ca1927-item-2":{"type":"item","settings":{"image":"shopify:\/\/shop_images\/Frame_297.svg","column_size":"3","title":"Wake","heading_tag":"h4","content":"<p>Move the joystick in any direction. It will appear as a discoverable accessory in your device’s Bluetooth settings.<\/p>","blob-color":"#0ec3ff","link_url":"","link_text":"","link_style":"link"}},"template--16346234257596__5c3c5d27-589a-469d-bbbe-474a58ca1927-item-3":{"type":"item","settings":{"image":"shopify:\/\/shop_images\/Frame_298.svg","column_size":"3","title":"Connect","heading_tag":"h4","content":"<p>With your smartphone or any other device such as sports cameras and wireless speakers and enjoy easy, handsfree control on the move, even when wearing gloves. <\/p>","blob-color":"#0ec3ff","link_url":"","link_text":"","link_style":"link"}}},"block_order":["template--16346234257596__5c3c5d27-589a-469d-bbbe-474a58ca1927-item-1","template--16346234257596__5c3c5d27-589a-469d-bbbe-474a58ca1927-item-2","template--16346234257596__5c3c5d27-589a-469d-bbbe-474a58ca1927-item-3"],"disabled":true,"settings":{"full_width":true,"stack_on_mobile":false,"blobs":true,"arrows-svg":false,"arrow-color":"#5252ff","gap":"medium","text_alignment":"center","subheading":"","header":"Quick steps start to use","header-color":"#5252ff","content":"<p>“ArcX is designed to work right out of the box but for additional functionality and to activate the SOS feature download the ArcX App. <\/p>","background":"","background_gradient":"","text_color":""}},"25838ecf-c9d4-44f2-86a3-5ef46b4516f3":{"type":"rich-text","blocks":{"template--16346234257596__25838ecf-c9d4-44f2-86a3-5ef46b4516f3-heading-1":{"type":"heading","settings":{"text":"Don't have ArcX yet?","heading_tag":"h1","text_color":"","gradient":""}},"template--16346234257596__25838ecf-c9d4-44f2-86a3-5ef46b4516f3-richtext-1":{"type":"richtext","settings":{"content":"<h5>Let's know about our device more<\/h5>"}}},"block_order":["template--16346234257596__25838ecf-c9d4-44f2-86a3-5ef46b4516f3-heading-1","template--16346234257596__25838ecf-c9d4-44f2-86a3-5ef46b4516f3-richtext-1"],"custom_css":[],"settings":{"full_width":true,"content_width":"large","text_position":"center","background":"","background_gradient":"","text_color":""}},"rich_text_amUpGG":{"type":"rich-text","blocks":{"heading_dYRjYk":{"type":"heading","settings":{"text":"The Smartest Ring","heading_tag":"h2","text_color":"","gradient":""}},"richtext_ptHpJY":{"type":"richtext","settings":{"content":"<p>All Benefits For You In One Device<\/p>"}}},"block_order":["heading_dYRjYk","richtext_ptHpJY"],"disabled":true,"settings":{"full_width":true,"content_width":"small","text_position":"center","background":"","background_gradient":"","text_color":""}},"a9498399-d7d8-4cbd-9f3f-50e2065b2959":{"type":"media-grid","blocks":{"e2e56360-923b-4040-9c5a-ce4b6fd69f32":{"type":"image","settings":{"tile-icon":"shopify:\/\/shop_images\/Frame_262.svg","title":"Intuitive control","body-text":"<p>ArcX’s inutitive design makes controlling your devices as natural as a thumb swipe. Easy to use even with gloves on.<\/p>","mobile-prose-color":"","text-align":"center","heading_tag":"h5","link_url":"","link_text":"","mobile_text_position":"place-self-center text-center","desktop_column_span":2,"desktop_row_span":1,"desktop_text_position":"sm:place-self-center sm:text-center","background":"#ffffff","background_gradient":"","text_color":"#1a1a1a","text_gradient":"","button_background":"#000000","button_text_color":"#ffffff","overlay_color":"#000000","overlay_opacity":0}},"image_CUwrUG":{"type":"image","settings":{"image":"shopify:\/\/shop_images\/ArcX_stretching_leg_1.png","title":"For active lifestyles","body-text":"<p>ArcX simplifies your active life. Whether you’re running, cycling or at the gym control your music seamlessly without missing a beat. No need to reach for your phone, with ArcX you'll enjoy hands free control. <\/p>","mobile-prose-color":"","text-align":"center","heading_tag":"h4","link_url":"","link_text":"","mobile_text_position":"place-self-center text-center","desktop_column_span":2,"desktop_row_span":2,"desktop_text_position":"sm:place-self-center sm:text-center","background":"#000000","background_gradient":"","text_color":"#ffffff","text_gradient":"","button_background":"#000000","button_text_color":"#ffffff","overlay_color":"#000000","overlay_opacity":0}},"image_iHWWAh":{"type":"image","settings":{"image":"shopify:\/\/shop_images\/Frame_315_2f7e4b9b-ed1c-4abf-9752-42cd1aab3bf4.svg","title":"Durability at its finest","body-text":"<p>Built to last, ArcX is water and shock proof ensuring durability in all your adventures. It’s so light you’ll forget you’re wearing it.<\/p>","mobile-prose-color":"","text-align":"center","heading_tag":"h2","link_url":"","link_text":"","mobile_text_position":"place-self-start-center text-center","desktop_column_span":2,"desktop_row_span":2,"desktop_text_position":"sm:place-self-start-center sm:text-center","background":"#000000","background_gradient":"","text_color":"#1a1a1a","text_gradient":"linear-gradient(136deg, rgba(14, 195, 255, 1) 11%, rgba(82, 82, 255, 1) 98%)","button_background":"#000000","button_text_color":"#ffffff","overlay_color":"#000000","overlay_opacity":0}},"79bf6712-209a-4c54-a65d-85f880db2b7d":{"type":"image","settings":{"tile-icon":"shopify:\/\/shop_images\/image_128.png","title":"Universal compatibility","body-text":"<p>Beyond music ArcX is your universal remote for any Bluetooth device. Control cameras, navigate presentations or mange smart home devices.<\/p>","mobile-prose-color":"","text-align":"center","heading_tag":"h5","link_url":"","link_text":"","mobile_text_position":"place-self-center text-center","desktop_column_span":2,"desktop_row_span":1,"desktop_text_position":"sm:place-self-center sm:text-center","background":"#ffffff","background_gradient":"","text_color":"#1a1a1a","text_gradient":"","button_background":"#000000","button_text_color":"#ffffff","overlay_color":"#000000","overlay_opacity":0}},"image_LgyrTh":{"type":"image","settings":{"tile-icon":"shopify:\/\/shop_images\/ezgif.com-animated-gif-maker_be8af2e8-5be7-4386-a9aa-ff4a84049551.gif","title":"Customisable and stylish","body-text":"<p>Match ArcX with your style. Available in a range of colours it’s not just a cool tech gadget but a fashion statement. Wear it on your finger or attached it to your gear - the choice is yours. <\/p>","mobile-prose-color":"","text-align":"center","heading_tag":"h4","link_url":"","link_text":"","mobile_text_position":"place-self-center text-center","desktop_column_span":2,"desktop_row_span":1,"desktop_text_position":"sm:place-self-center sm:text-center","background":"#ffffff","background_gradient":"","text_color":"#1a1a1a","text_gradient":"","button_background":"#000000","button_text_color":"#ffffff","overlay_color":"#000000","overlay_opacity":0}},"ea4e4b3c-0a05-4bf3-9e33-016d9beb5029":{"type":"image","settings":{"tile-icon":"shopify:\/\/shop_images\/sos.svg","title":"Ready for everything","body-text":"<p>Stay safe with ArcX’s built in SOS button. A discreet yet powerful tool to ensure help is just a press away in any situation. <\/p>","mobile-prose-color":"","text-align":"center","heading_tag":"h5","link_url":"","link_text":"","mobile_text_position":"place-self-center text-center","desktop_column_span":2,"desktop_row_span":1,"desktop_text_position":"sm:place-self-center sm:text-center","background":"#ffffff","background_gradient":"","text_color":"#1a1a1a","text_gradient":"","button_background":"#000000","button_text_color":"#ffffff","overlay_color":"#000000","overlay_opacity":0}}},"block_order":["e2e56360-923b-4040-9c5a-ce4b6fd69f32","image_CUwrUG","image_iHWWAh","79bf6712-209a-4c54-a65d-85f880db2b7d","image_LgyrTh","ea4e4b3c-0a05-4bf3-9e33-016d9beb5029"],"settings":{"full_width":true,"reduce_width":false,"desktop_row_height":290,"mobile_row_height":150,"background":"","background_gradient":""}},"custom_html_FTND4e":{"type":"custom-html","settings":{"full_width":true,"remove_vertical_spacing":true,"remove_horizontal_spacing":true,"html":"<name id=\"bottom\">\n<a name=\"bottom\" id=\"bottom\"><\/a><\/name>","background":"","background_gradient":"","text_color":""}},"ceb7eb10-b55c-491a-9b85-461d2b185d7c":{"type":"featured-product","blocks":{"template--16346234257596__ceb7eb10-b55c-491a-9b85-461d2b185d7c-vendor-1":{"type":"vendor","settings":{}},"template--16346234257596__ceb7eb10-b55c-491a-9b85-461d2b185d7c-title-1":{"type":"title","settings":{"heading_tag":"h2"}},"template--16346234257596__ceb7eb10-b55c-491a-9b85-461d2b185d7c-badges-1":{"type":"badges","settings":{}},"template--16346234257596__ceb7eb10-b55c-491a-9b85-461d2b185d7c-price-1":{"type":"price","settings":{"show_taxes_notice":false}},"offer_ezH9qE":{"type":"offer","settings":{"text_alignment":"start","icon_position":"aligned","icon":"none","icon_width":24,"title":"","content":"<p><strong>Easy, hands free remote control of any Bluetooth device<\/strong><\/p>","background":"#d4eff8","text_color":"#1a1a1a"}},"template--16346234257596__ceb7eb10-b55c-491a-9b85-461d2b185d7c-rating-1":{"type":"rating","settings":{"show_empty":false}},"template--16346234257596__ceb7eb10-b55c-491a-9b85-461d2b185d7c-separator-1":{"type":"separator","settings":{}},"template--16346234257596__ceb7eb10-b55c-491a-9b85-461d2b185d7c-variant_picker-1":{"type":"variant_picker","settings":{"hide_sold_out_variants":false,"stack_blocks":true,"selector_mode":"block","color_mode":"color","size_chart_page":""}},"template--16346234257596__ceb7eb10-b55c-491a-9b85-461d2b185d7c-quantity_selector-1":{"type":"quantity_selector","settings":{}},"template--16346234257596__ceb7eb10-b55c-491a-9b85-461d2b185d7c-buy_buttons-1":{"type":"buy_buttons","settings":{"show_payment_button":true,"show_gift_card_recipient":true,"atc_button_background":"","atc_button_text_color":"","payment_button_background":"","payment_button_text_color":""}},"text_6dytxj":{"type":"text","settings":{"text":"<p>📦<strong>Free delivery |<\/strong>💯<strong>30 day money back guarantee | <\/strong>✅<strong>1 year warranty<\/strong><\/p>"}},"template--16346234257596__ceb7eb10-b55c-491a-9b85-461d2b185d7c-pickup_availability-1":{"type":"pickup_availability","settings":{}},"template--16346234257596__ceb7eb10-b55c-491a-9b85-461d2b185d7c-description-1":{"type":"description","settings":{"collapse_content":true}}},"block_order":["template--16346234257596__ceb7eb10-b55c-491a-9b85-461d2b185d7c-vendor-1","template--16346234257596__ceb7eb10-b55c-491a-9b85-461d2b185d7c-title-1","template--16346234257596__ceb7eb10-b55c-491a-9b85-461d2b185d7c-badges-1","template--16346234257596__ceb7eb10-b55c-491a-9b85-461d2b185d7c-price-1","offer_ezH9qE","template--16346234257596__ceb7eb10-b55c-491a-9b85-461d2b185d7c-rating-1","template--16346234257596__ceb7eb10-b55c-491a-9b85-461d2b185d7c-separator-1","template--16346234257596__ceb7eb10-b55c-491a-9b85-461d2b185d7c-variant_picker-1","template--16346234257596__ceb7eb10-b55c-491a-9b85-461d2b185d7c-quantity_selector-1","template--16346234257596__ceb7eb10-b55c-491a-9b85-461d2b185d7c-buy_buttons-1","text_6dytxj","template--16346234257596__ceb7eb10-b55c-491a-9b85-461d2b185d7c-pickup_availability-1","template--16346234257596__ceb7eb10-b55c-491a-9b85-461d2b185d7c-description-1"],"settings":{"full_width":false,"product":"arcx-smart-ring","desktop_media_width":50,"desktop_media_layout":"carousel_thumbnails_bottom","mobile_media_size":"contained","mobile_carousel_control":"thumbnails","enable_video_autoplay":true,"enable_video_looping":false,"enable_image_zoom":true,"max_image_zoom_level":3,"background":"#fcfcfc","background_gradient":"","text_color":"#1a1a1a","input_background":"rgba(0,0,0,0)","input_text_color":""}},"9adbabda-1972-4df0-8585-9aabcd93c110":{"type":"UGC","blocks":{"42c2e224-bf26-42de-8b8e-8342156b8a34":{"type":"tab","settings":{"poster_img":"shopify:\/\/shop_images\/1.jpg","poster_url":"","video_url":"https:\/\/cdn.shopify.com\/videos\/c\/o\/v\/d1d72bcd6c414044b4414d59f5415432.mp4"}},"d696f959-6bc8-47dc-acbd-97fae0600a13":{"type":"tab","settings":{"poster_img":"shopify:\/\/shop_images\/11.jpg","poster_url":"","video_url":"https:\/\/cdn.shopify.com\/videos\/c\/o\/v\/4a0b1863aa33446b8c33e487b816ff2b.mp4"}},"56ce0eb9-5ffb-452b-bb51-7d2cf2d06aa4":{"type":"tab","settings":{"poster_img":"shopify:\/\/shop_images\/8.jpg","poster_url":"","video_url":"https:\/\/cdn.shopify.com\/videos\/c\/o\/v\/934a62b3f9be47ed83c73d5fa5de2ce7.mp4"}},"b52e838f-4b94-49b3-9ab6-8c0f98f83009":{"type":"tab","settings":{"poster_img":"shopify:\/\/shop_images\/2.jpg","poster_url":"","video_url":"https:\/\/cdn.shopify.com\/videos\/c\/o\/v\/f441f5996d684d62b7b2d5488459ac83.mp4"}},"e484c31f-59c9-4a86-9df2-7621058a3f46":{"type":"tab","settings":{"poster_img":"shopify:\/\/shop_images\/9.jpg","poster_url":"","video_url":"https:\/\/cdn.shopify.com\/videos\/c\/o\/v\/d1d72bcd6c414044b4414d59f5415432.mp4"}},"934df4d3-81fa-499d-b4a7-86cd7f63ab0d":{"type":"tab","settings":{"poster_img":"shopify:\/\/shop_images\/3.jpg","poster_url":"","video_url":"https:\/\/cdn.shopify.com\/videos\/c\/o\/v\/e3619467262b4de7b9dcb03ab3622e40.mp4"}},"6802d9ca-8a6d-4a80-932d-5dd70cffcb73":{"type":"tab","settings":{"poster_img":"shopify:\/\/shop_images\/7.jpg","poster_url":"","video_url":"https:\/\/cdn.shopify.com\/videos\/c\/o\/v\/5386a77d70de4329b2d645a768e189b3.mp4"}},"176172e0-2c3d-4c01-8ecd-aa8ab8160d87":{"type":"tab","settings":{"poster_img":"shopify:\/\/shop_images\/5.jpg","poster_url":"","video_url":"https:\/\/cdn.shopify.com\/videos\/c\/o\/v\/108312ed04d24d74a1a74e040088b513.mp4"}},"8d788e1f-c6dd-48d4-aa1f-3203f76426e2":{"type":"tab","settings":{"poster_img":"shopify:\/\/shop_images\/10.jpg","poster_url":"","video_url":"https:\/\/cdn.shopify.com\/videos\/c\/o\/v\/00c48b69e79b4bbaa006fae6bcc92fa6.mp4"}},"872a5e27-518a-4bf4-bd31-ffe6addc39d3":{"type":"tab","settings":{"poster_img":"shopify:\/\/shop_images\/4.jpg","poster_url":"","video_url":"https:\/\/cdn.shopify.com\/videos\/c\/o\/v\/371114da08f74f3e8503da95f3143c0f.mp4"}}},"block_order":["42c2e224-bf26-42de-8b8e-8342156b8a34","d696f959-6bc8-47dc-acbd-97fae0600a13","56ce0eb9-5ffb-452b-bb51-7d2cf2d06aa4","b52e838f-4b94-49b3-9ab6-8c0f98f83009","e484c31f-59c9-4a86-9df2-7621058a3f46","934df4d3-81fa-499d-b4a7-86cd7f63ab0d","6802d9ca-8a6d-4a80-932d-5dd70cffcb73","176172e0-2c3d-4c01-8ecd-aa8ab8160d87","8d788e1f-c6dd-48d4-aa1f-3203f76426e2","872a5e27-518a-4bf4-bd31-ffe6addc39d3"],"settings":{"allowScroll":false,"header":"<h1>See Us in Action<\/h1>","header_color":"#1a1a1a","body_text":"<p>Unlock the Power of Customer Satisfaction! 🌟 Discover why our customers can't stop raving about our device. Join the legion of satisfied users who have experienced the difference firsthand<\/p>","bodytext_color":"#1a1a1a","background-color":"#ffffff","background-gradient":""}},"5de6c540-bad8-4d59-ae6e-fc502421949a":{"type":"press","blocks":{"template--16346234257596__5de6c540-bad8-4d59-ae6e-fc502421949a-quote-1":{"type":"quote","settings":{"logo_width":100,"author":"Jessica Maiklem ESF Ski and snowboard instructor and alpine ski racer","content":"\"A great piece of kit. I can keep my phone secure and ArcX gives me piece of mind when ski touring with the SOS system.\"","show_rating":false,"rating":4}},"template--16346234257596__5de6c540-bad8-4d59-ae6e-fc502421949a-quote-2":{"type":"quote","settings":{"logo_width":100,"author":"Jaco Van Gass MBE  Adventurer, World and Paralympic champion cyclist, veteran","content":"\"Brilliant concept. ArcX is easy to set up, easy to use and does what it needs to.\"","show_rating":false,"rating":4}},"template--16346234257596__5de6c540-bad8-4d59-ae6e-fc502421949a-quote-3":{"type":"quote","settings":{"logo_width":100,"author":"Constantine Louloudis MBE  Olympic and double world champion rower","content":"\"I wish I had this when I was training for the Olympics.\"","show_rating":false,"rating":4}},"02b8a963-918f-4359-87fa-584eb724081a":{"type":"quote","settings":{"logo_width":100,"author":"Alex Gray  TV presenter, actress","content":"\"No more fiddling with my phone and headphones to adjust music on my runs. ArcX is revolutionary.\"","show_rating":false,"rating":4}},"6c044e78-7022-4d55-9d54-188afb493c78":{"type":"quote","settings":{"logo_width":100,"author":"Giles Timms  Ultra runner","content":"\"Light as a feather and perfect for controlling my music during training. ArcX is a must for every runner.\"","show_rating":false,"rating":4}},"53c3f6fb-da9e-452a-b7da-888eedcceeaf":{"type":"quote","settings":{"logo_width":100,"author":"Joey Chase  Firefighter, fitness instructor, model and actor","content":"\"This is game changing.\"","show_rating":false,"rating":4}}},"block_order":["template--16346234257596__5de6c540-bad8-4d59-ae6e-fc502421949a-quote-1","template--16346234257596__5de6c540-bad8-4d59-ae6e-fc502421949a-quote-2","template--16346234257596__5de6c540-bad8-4d59-ae6e-fc502421949a-quote-3","02b8a963-918f-4359-87fa-584eb724081a","6c044e78-7022-4d55-9d54-188afb493c78","53c3f6fb-da9e-452a-b7da-888eedcceeaf"],"settings":{"full_width":true,"content_size":"medium","background":"","background_gradient":"","text_color":"","heading_color":"","heading_gradient":"","logo_item_background":"","logo_item_border":""}},"42dad7dd-f6af-4545-887a-b2ffb2db56d2":{"type":"joystick","blocks":{"b0fe863e-0dfe-4884-9de2-db910c3493ca":{"type":"tab","settings":{"direction-text":"Toggle Up"}},"dd071af8-47c0-41cb-a14d-c74146e5967d":{"type":"tab","settings":{"direction-text":"Toggle Left"}},"906dee16-5129-4092-8316-90d4511b7f4f":{"type":"tab","settings":{"direction-text":"Toggle Right"}},"dcd26d4d-5872-4c44-9297-60db898860d1":{"type":"tab","settings":{"direction-text":"Toggle Down"}}},"block_order":["b0fe863e-0dfe-4884-9de2-db910c3493ca","dd071af8-47c0-41cb-a14d-c74146e5967d","906dee16-5129-4092-8316-90d4511b7f4f","dcd26d4d-5872-4c44-9297-60db898860d1"],"disabled":true,"settings":{"background_color":"#ffffff","background_gradient":"","header-color":"#5252ff","main-image":"shopify:\/\/shop_images\/0e1e31279d136c88dbf7363383ce8487.png","header":"<h1>Easy to Navigate<\/h1>","body-text":"<p>body text body text body text body text body text body text body text body text body text body text body text body text body text body text body text body text body text body text body text body text body text body text body text body text body text body text body text <\/p>","prose-text":"","prose_color":"#ffffff","direction-bg":"#0ec3ff","direction-color":"#ffffff","direction-hover-bg":"#1a1a1a","direction-hover-color":"#ffffff"}},"3d6f85c1-8905-4199-aecf-e0ee60579221":{"type":"testimonials","blocks":{"template--16346234257596__3d6f85c1-8905-4199-aecf-e0ee60579221-testimonial-1":{"type":"testimonial","settings":{"image":"shopify:\/\/shop_images\/logos_facebook.svg","round_avatar":true,"show_rating":true,"rating":5,"author":"J. Pittaway","title":"Addicted","content":"<p>\"Brilliant piece of kit\"<\/p>"}},"template--16346234257596__3d6f85c1-8905-4199-aecf-e0ee60579221-testimonial-2":{"type":"testimonial","settings":{"image":"shopify:\/\/shop_images\/logos_facebook.svg","round_avatar":true,"show_rating":true,"rating":5,"author":"C. Bruce","title":"Pure delight","content":"<p>\"You've nailed it, it's really, really good\"<\/p>"}},"template--16346234257596__3d6f85c1-8905-4199-aecf-e0ee60579221-testimonial-3":{"type":"testimonial","settings":{"image":"shopify:\/\/shop_images\/logos_facebook.svg","round_avatar":true,"show_rating":true,"rating":5,"author":"J. Nemo","title":"Very satisfied","content":"<p>\"It's awesome\"<\/p>"}},"5bb305b8-fdf0-4d48-a306-8dd604e64c33":{"type":"testimonial","settings":{"image":"shopify:\/\/shop_images\/logos_facebook.svg","round_avatar":true,"show_rating":true,"rating":5,"author":"I. Ballantyne","title":"Irreplaceable device","content":"<p>\"I love it for my gym and bike playlists\"<\/p>"}}},"block_order":["template--16346234257596__3d6f85c1-8905-4199-aecf-e0ee60579221-testimonial-1","template--16346234257596__3d6f85c1-8905-4199-aecf-e0ee60579221-testimonial-2","template--16346234257596__3d6f85c1-8905-4199-aecf-e0ee60579221-testimonial-3","5bb305b8-fdf0-4d48-a306-8dd604e64c33"],"settings":{"full_width":true,"stack_testimonials":false,"subheading":"","title":"What owners say about us","content":"","link_url":"","link_text":"","background":"","background_gradient":"","text_color":"","heading_color":"","heading_gradient":"","testimonial_card_background":"#ffffff","testimonial_card_text_color":""}},"rich_text_4ncYUN":{"type":"rich-text","blocks":{"heading_xHpxLR":{"type":"heading","settings":{"text":"Know more about our Smart Ring","heading_tag":"h2","text_color":"","gradient":""}},"richtext_yxfYMd":{"type":"richtext","settings":{"content":"<p>Unlock the Future on Your Finger!  Discover the Magic of Smart Rings Now. Tap to Explore and Elevate Your Lifestyle!<\/p>"}},"button_KQ6Xek":{"type":"button","settings":{"style":"fill","size":"xl","text":"Go to ArcX","url":"","background":"","text_color":""}}},"block_order":["heading_xHpxLR","richtext_yxfYMd","button_KQ6Xek"],"custom_css":["{background: url(\"https:\/\/cdn.shopify.com\/s\/files\/1\/0589\/0018\/5276\/files\/Frame_274_15bbabf1-821c-422b-b03e-23bf0cf2b44a.png?v=1704809053\") no-repeat center; background-size: cover;}"],"settings":{"full_width":true,"content_width":"medium","text_position":"center","background":"","background_gradient":"","text_color":""}},"11619800-ae54-4336-bbd4-6ad87a9fd88f":{"type":"image-link-blocks","blocks":{"template--16346234257596__11619800-ae54-4336-bbd4-6ad87a9fd88f-item-1":{"type":"item","settings":{"image":"shopify:\/\/shop_images\/Frame_269.png","stretch_image":true,"link_text":"","link_url":"","background":"","text_color":"#ffffff","overlay_color":"#000000","overlay_opacity":0}},"template--16346234257596__11619800-ae54-4336-bbd4-6ad87a9fd88f-item-2":{"type":"item","settings":{"image":"shopify:\/\/shop_images\/Frame_270.png","stretch_image":true,"link_text":"","link_url":"","background":"","text_color":"#ffffff","overlay_color":"#000000","overlay_opacity":0}},"template--16346234257596__11619800-ae54-4336-bbd4-6ad87a9fd88f-item-3":{"type":"item","settings":{"image":"shopify:\/\/shop_images\/Frame_271.png","stretch_image":true,"link_text":"","link_url":"","background":"","text_color":"#ffffff","overlay_color":"#000000","overlay_opacity":0}},"template--16346234257596__11619800-ae54-4336-bbd4-6ad87a9fd88f-item-4":{"type":"item","settings":{"image":"shopify:\/\/shop_images\/Frame_272.png","stretch_image":true,"link_text":"","link_url":"","background":"","text_color":"#ffffff","overlay_color":"#000000","overlay_opacity":0}},"74f254aa-2f0e-4a96-9825-75fb2a87b9ce":{"type":"item","settings":{"image":"shopify:\/\/shop_images\/Frame_273.png","stretch_image":true,"link_text":"","link_url":"","background":"","text_color":"#ffffff","overlay_color":"#000000","overlay_opacity":0}}},"block_order":["template--16346234257596__11619800-ae54-4336-bbd4-6ad87a9fd88f-item-1","template--16346234257596__11619800-ae54-4336-bbd4-6ad87a9fd88f-item-2","template--16346234257596__11619800-ae54-4336-bbd4-6ad87a9fd88f-item-3","template--16346234257596__11619800-ae54-4336-bbd4-6ad87a9fd88f-item-4","74f254aa-2f0e-4a96-9825-75fb2a87b9ce"],"settings":{"full_width":false,"center-blocks":false,"block_size":"medium","subheading":"","title":"Our awards:","content":"","link_url":"","link_text":"","background":"","background_gradient":"","text_color":"","heading_color":"","heading_gradient":""}},"8d618655-1e59-4bc4-a27e-6e4334487b64":{"type":"faq","blocks":{"template--16346234257596__8d618655-1e59-4bc4-a27e-6e4334487b64-item-1":{"type":"item","settings":{"title":"How long does ArcX take to charge?","content":"<p>ArcX takes about 60 minutes to fully charge.<\/p>"}},"template--16346234257596__8d618655-1e59-4bc4-a27e-6e4334487b64-item-2":{"type":"item","settings":{"title":"How will ArcX perform in salt water?","content":"<p>In the same way you take care of other devices such as sports cameras, we recommend rinsing with fresh water after use in salt water, so with care you will not have any problems. <\/p>"}},"template--16346234257596__8d618655-1e59-4bc4-a27e-6e4334487b64-item-3":{"type":"item","settings":{"title":"How do I turn the ArcX ring off?","content":"<p>There is no need to turn your ring off. The ArcX ring is programmed to go to sleep after 120 seconds of inactivity.  When in sleep mode the battery will last for &gt;20 days on a single charge. To wake just move the joystick once in any direction, your ArcX will then continue to function as normal.<\/p>"}},"item_Nz3Tqn":{"type":"item","settings":{"title":"What is the ArcX operating range?","content":"<p>Your ArcX will work to a range of at least 25m (82 ft). We’ve tested ArcX extensively and in numerous scenarios. For example, during an outdoor group workout in a busy central London park, ArcX worked well controlling a wireless speaker 100m (328 ft) away.<\/p>"}},"item_phY6BL":{"type":"item","settings":{"title":"What kind of battery does ArcX use?","content":"<p>ArcX uses a high-quality lithium polymer rechargeable battery. Like your phone battery, the ArcX battery is fully integrated into the tech module. The battery will last up to five days of normal use on a single charge and at least twenty days on standby;<\/p>"}},"item_HzJX4W":{"type":"item","settings":{"title":"Will customers be able to update their software in future?","content":"<p>The short answer is yes! We will release not only bug fixes but also significant new features via regular <strong>Over The Air (OTA) <\/strong>software updates and your ArcX will continue to get better over time. New software features, such as integration with other sports and fitness Apps, will not require any additional hardware purchases.<\/p>"}},"item_cDtBMd":{"type":"item","settings":{"title":"Is ArcX suitable for kids?","content":"<p>Children can absolutely use ArcX! With its single handed operation and intuitive UX our smart ring is simple to operate so it's suitable even for younger children (depending on their finger size). <\/p>"}},"item_reBXKQ":{"type":"item","settings":{"title":"I do not see my country listed as a shipping option.","content":"<p>If you do not see your country as a shipping option, it means that we currently do not offer shipping to that country. We are working hard to add more countries to the list. However, please send us an email if you are from a country that is not shown, we'd love to hear from you.<\/p>"}},"item_tUJzCK":{"type":"item","settings":{"title":"I am a retailer, how can I stock ArcX?","content":"<p>For retailers interested in stocking ArcX smart rings and for a full list of prices and information please contact us at hello@arcx.fit.<\/p>"}},"item_FAWVUJ":{"type":"item","settings":{"title":"I have another question that isn't listed here!","content":"<p>If you have any questions, feedback, or simply want to say hello, drop us a line at  hello@arcx.fit.<\/p>"}}},"block_order":["template--16346234257596__8d618655-1e59-4bc4-a27e-6e4334487b64-item-1","template--16346234257596__8d618655-1e59-4bc4-a27e-6e4334487b64-item-2","template--16346234257596__8d618655-1e59-4bc4-a27e-6e4334487b64-item-3","item_Nz3Tqn","item_phY6BL","item_HzJX4W","item_cDtBMd","item_reBXKQ","item_tUJzCK","item_FAWVUJ"],"settings":{"full_width":false,"subheading":"","title":"Have a question ? We are here to help.","content":"","team_avatar_width":160,"support_hours":"Our customer support is available Monday to Friday: 8am-8:30pm.","answer_time":"Average answer time: 24h","button_text":"","button_url":"","text_position":"start","background":"#1a1a1a","background_gradient":"","text_color":"#ffffff","heading_color":"","heading_gradient":"","button_background":"","button_text_color":"","accordion_background":"#fcfcfc","accordion_text_color":"#1a1a1a"}}},"order":["main","d9d08b5d-a836-459e-8579-0fd215508612","8179674e-8606-4b6b-85f8-5b3d943ebb4c","5c3c5d27-589a-469d-bbbe-474a58ca1927","25838ecf-c9d4-44f2-86a3-5ef46b4516f3","rich_text_amUpGG","a9498399-d7d8-4cbd-9f3f-50e2065b2959","custom_html_FTND4e","ceb7eb10-b55c-491a-9b85-461d2b185d7c","9adbabda-1972-4df0-8585-9aabcd93c110","5de6c540-bad8-4d59-ae6e-fc502421949a","42dad7dd-f6af-4545-887a-b2ffb2db56d2","3d6f85c1-8905-4199-aecf-e0ee60579221","rich_text_4ncYUN","11619800-ae54-4336-bbd4-6ad87a9fd88f","8d618655-1e59-4bc4-a27e-6e4334487b64"]}